bertdotconfig/__init__.py
bertdotconfig/configloader.py
bertdotconfig/configutils.py
bertdotconfig/logger.py
bertdotconfig/superconf.py
bertdotconfig-4.4.0.dist-info/METADATA
bertdotconfig-4.4.0.dist-info/WHEEL
bertdotconfig-4.4.0.dist-info/top_level.txt
bertdotconfig-4.4.0.dist-info/RECORD
